easydev/__init__.py
easydev/appdirs.py
easydev/browser.py
easydev/chunks.py
easydev/codecs.py
easydev/config_tools.py
easydev/console.py
easydev/copybutton.py
easydev/decorators.py
easydev/dependencies.py
easydev/doc.py
easydev/easytest.py
easydev/logging_tools.py
easydev/md5tools.py
easydev/misc.py
easydev/multicore.py
easydev/options.py
easydev/paths.py
easydev/platform.py
easydev/profiler.py
easydev/progressbar.py
easydev/share/__init__.py
easydev/share/copybutton.js
easydev/share/themes/cno/google_footer.html
easydev/share/themes/cno/google_head.html
easydev/share/themes/cno/index.html
easydev/share/themes/cno/indexsidebar.html
easydev/share/themes/cno/layout.html
easydev/share/themes/cno/static/bgfooter.png
easydev/share/themes/cno/static/bgtop.png
easydev/share/themes/cno/static/software.css_t
easydev/share/themes/cno/static/warning.jpg
easydev/share/themes/cno/theme.conf
easydev/share/themes/standard/google_footer.html
easydev/share/themes/standard/google_head.html
easydev/share/themes/standard/index.html
easydev/share/themes/standard/indexsidebar.html
easydev/share/themes/standard/layout.html
easydev/share/themes/standard/static/bgfooter.png
easydev/share/themes/standard/static/bgtop.png
easydev/share/themes/standard/static/software.css_t
easydev/share/themes/standard/static/warning.jpg
easydev/share/themes/standard/theme.conf
easydev/sphinx_themes.py
easydev/timer.py
easydev/tools.py
easydev/url.py
easydev-0.13.0.dist-info/COPYING
easydev-0.13.0.dist-info/METADATA
easydev-0.13.0.dist-info/WHEEL
easydev-0.13.0.dist-info/RECORD
