Metadata-Version: 2.1
Name: easydev
Version: 0.13.0
Summary: Commn utilities to ease development of Python packages
License: BSD-3-Clause
Keywords: config,decorators,development
Author: Thomas Cokelaer
Author-email: thomas.cokelaer@pasteur.fr
Requires-Python: >=3.8,<4.0
Classifier: Development Status :: 5 - Production/Stable
Classifier: Intended Audience :: Developers
Classifier: Intended Audience :: Education
Classifier: Intended Audience :: End Users/Desktop
Classifier: Intended Audience :: Science/Research
Classifier: License :: OSI Approved :: BSD License
Classifier: Operating System :: POSIX :: Linux
Classifier: Programming Language :: Python :: 3
Classifier: Programming Language :: Python :: 3.8
Classifier: Programming Language :: Python :: 3.9
Classifier: Programming Language :: Python :: 3.10
Classifier: Programming Language :: Python :: 3.11
Classifier: Programming Language :: Python :: 3.10
Classifier: Programming Language :: Python :: 3.11
Classifier: Programming Language :: Python :: 3.8
Classifier: Programming Language :: Python :: 3.9
Classifier: Topic :: Scientific/Engineering :: Bio-Informatics
Classifier: Topic :: Scientific/Engineering :: Information Analysis
Classifier: Topic :: Software Development :: Libraries :: Python Modules
Requires-Dist: colorama (>=0.4.6,<0.5.0)
Requires-Dist: colorlog (>=6.8.2,<7.0.0)
Requires-Dist: line-profiler (>=4.1.2,<5.0.0)
Requires-Dist: pexpect (>=4.9.0,<5.0.0)
Requires-Dist: platformdirs (>=4.2.0,<5.0.0)
